sparekeys/__init__.py
sparekeys/default_config.toml
sparekeys/main.py
sparekeys-0.2.0.dist-info/entry_points.txt
sparekeys-0.2.0.dist-info/LICENSE.txt
sparekeys-0.2.0.dist-info/WHEEL
sparekeys-0.2.0.dist-info/METADATA
sparekeys-0.2.0.dist-info/RECORD
