Metadata-Version: 2.1
Name: sparekeys
Version: 0.2.0
Summary: Make and distribute encrypted copies of the files that you would need to 
Home-page: https://github.com/kalekundert/sparekeys
License: UNKNOWN
Author: Kale Kundert
Author-email: kale@thekunderts.net
Requires-Python: ~=3.6
Classifier: Programming Language :: Python :: 3
Classifier: License :: OSI Approved :: GNU General Public License v3 or later (GPLv3+)
Classifier: Natural Language :: English
Classifier: Topic :: Utilities
Requires-Dist: inform>=1.14
Requires-Dist: shlib>=1.0
Requires-Dist: setuptools
Requires-Dist: toml
Requires-Dist: appdirs
Requires-Dist: docopt
Requires-Dist: python-gnupg>=0.4.3
Requires-Dist: sphinx ; extra == "docs"
Requires-Dist: sphinx_rtd_theme ; extra == "docs"
Requires-Dist: autoclasstoc ; extra == "docs"
Requires-Dist: pytest ; extra == "tests"
Requires-Dist: pytest-cov ; extra == "tests"
Requires-Dist: coveralls ; extra == "tests"
Project-URL: Bug Tracker, https://github.com/kalekundert/sparekeys/issues
Project-URL: Continuous Integration, https://github.com/kalekundert/sparekeys/actions
Project-URL: Documentation, https://sparekeys.readthedocs.io/en/latest/
Project-URL: Test Coverage, https://coveralls.io/github/kalekundert/sparekeys
Project-URL: Version Control, https://github.com/kalekundert/sparekeys
Provides-Extra: docs
Provides-Extra: tests
